route_graph/__init__.py
route_graph/exceptions.py
route_graph/main.py
route_graph-0.2.2.dist-info/LICENSE
route_graph-0.2.2.dist-info/METADATA
route_graph-0.2.2.dist-info/WHEEL
route_graph-0.2.2.dist-info/entry_points.txt
route_graph-0.2.2.dist-info/RECORD
