Metadata-Version: 2.1
Name: route-graph
Version: 0.2.2
Summary: Tool for creating graphs of routes
Home-page: https://github.com/audiusGmbH/route-graph
License: MIT
Keywords: traceroute,graph,routes
Author: Fabian Affolter
Author-email: mail@fabian-affolter.ch
Requires-Python: >=3.10,<4.0
Classifier: License :: OSI Approved :: MIT License
Classifier: Programming Language :: Python :: 3
Classifier: Programming Language :: Python :: 3.10
Classifier: Programming Language :: Python :: 3.11
Classifier: Programming Language :: Python :: 3.12
Requires-Dist: scapy (>=2.5.0,<3.0.0)
Requires-Dist: typer (>=0.12,<0.13)
Requires-Dist: typing-extensions (>=4.10.0,<5.0.0)
Project-URL: Repository, https://github.com/audiusGmbH/route-graph
